hteetp/__about__.py
hteetp/__init__.py
hteetp/__init__.py~
hteetp/readfile.py
hteetp/readfile.py~
hteetp/request.py
hteetp/request.py~
hteetp/teeconn.py
hteetp/teeconn.py~
hteetp/teereader.py
hteetp-0.1.dist-info/METADATA
hteetp-0.1.dist-info/WHEEL
hteetp-0.1.dist-info/licenses/LICENSE.txt
hteetp-0.1.dist-info/RECORD
