Metadata-Version: 2.1
Name: hteetp
Version: 0.1
Project-URL: Documentation, https://github.com/unknown/hteetp#readme
Project-URL: Issues, https://github.com/unknown/hteetp/issues
Project-URL: Source, https://github.com/unknown/hteetp
Author-email: Spencer Nelson <spencer@b612foundation.org>
License-Expression: MIT
License-File: LICENSE.txt
Classifier: Development Status :: 4 - Beta
Classifier: Programming Language :: Python
Classifier: Programming Language :: Python :: 3.10
Classifier: Programming Language :: Python :: 3.11
Classifier: Programming Language :: Python :: Implementation :: CPython
Classifier: Programming Language :: Python :: Implementation :: PyPy
Requires-Python: >=3.10
